tgflow/TgFlow.py
tgflow/__init__.py
tgflow/coffee_ui.py
tgflow/core.py
tgflow/handles.py
tgflow/render.py
tgflow/sandbox.py
tgflow/test.py
tgflow/test_render.py
tgflow/tests.__init__.py
tgflow/api/Types.py
tgflow/api/__init__.py
tgflow/api/base.py
tgflow/api/cli.py
tgflow/api/cli_bot.py
tgflow/api/longpoll.py
tgflow/api/tg.py
tgflow/api/vk.py
tgflow/api/vk_bot.py
tgflow-0.3.5.dist-info/METADATA
tgflow-0.3.5.dist-info/RECORD
tgflow-0.3.5.dist-info/WHEEL
tgflow-0.3.5.dist-info/top_level.txt
