Metadata-Version: 2.1
Name: tgflow
Version: 0.3.5
Summary: A declarative-style telegram bot framework
Home-page: https://github.com/DaniloZZZ/tgflow
Author: Danil Lykov
Author-email: lkvdan@gmail.com
License: MIT
Download-URL: https://github.com/DaniloZZZ/tgflow/archive/0.1.tar.gz
Keywords: tools,telegram,framework,bot
Platform: UNKNOWN
Requires-Dist: pyTelegramBotAPI
